garminconnect/__init__.py
garminconnect/fit.py
garminconnect/workout.py
garminconnect_uv-0.2.38.dist-info/METADATA
garminconnect_uv-0.2.38.dist-info/WHEEL
garminconnect_uv-0.2.38.dist-info/licenses/LICENSE
garminconnect_uv-0.2.38.dist-info/RECORD
