Metadata-Version: 2.4
Name: garminconnect-uv
Version: 0.2.38
Summary: Python 3 API wrapper for Garmin Connect using UV
Project-URL: Homepage, https://github.com/cyberjunky/python-garminconnect
Project-URL: Issues, https://github.com/cyberjunky/python-garminconnect/issues
Project-URL: Changelog, https://github.com/cyberjunky/python-garminconnect/releases
Author-email: Ron Klinkien <ron@cyberjunky.nl>
License: MIT
License-File: LICENSE
Keywords: api,garmin,garmin connect
Classifier: Development Status :: 5 - Production/Stable
Classifier: License :: OSI Approved :: MIT License
Classifier: Operating System :: MacOS :: MacOS X
Classifier: Operating System :: Microsoft :: Windows
Classifier: Operating System :: OS Independent
Classifier: Operating System :: POSIX :: Linux
Classifier: Programming Language :: Python :: 3.10
Classifier: Programming Language :: Python :: 3.11
Classifier: Programming Language :: Python :: 3.12
Classifier: Programming Language :: Python :: 3.13
Requires-Python: >=3.10
Requires-Dist: garth<0.6.0,>=0.5.17
Provides-Extra: dev
Requires-Dist: ipdb; extra == 'dev'
Requires-Dist: ipykernel; extra == 'dev'
Requires-Dist: ipython; extra == 'dev'
Requires-Dist: matplotlib; extra == 'dev'
Requires-Dist: pandas; extra == 'dev'
Provides-Extra: example
Requires-Dist: garth<0.6.0,>=0.5.17; extra == 'example'
Requires-Dist: readchar; extra == 'example'
Requires-Dist: requests; extra == 'example'
Provides-Extra: linting
Requires-Dist: black[jupyter]; extra == 'linting'
Requires-Dist: isort; extra == 'linting'
Requires-Dist: mypy; extra == 'linting'
Requires-Dist: ruff; extra == 'linting'
Requires-Dist: types-requests; extra == 'linting'
Provides-Extra: testing
Requires-Dist: coverage; extra == 'testing'
Requires-Dist: pytest; extra == 'testing'
Requires-Dist: pytest-vcr>=1.0.2; extra == 'testing'
Requires-Dist: vcrpy>=7.0.0; extra == 'testing'
Provides-Extra: workout
Requires-Dist: pydantic>=2.0.0; extra == 'workout'
